Workbook

Sheet groupe
A1: ETU003362 | B1: Tojo

Sheet liste des taches
A1: Ligne | B1: Categorie | C1: Module | D1: Page | E1: Description tache | F1: Type | G1: Qui | H1: Estimation | I1: Temps passe | J1: Reste a faire | K1: Avancement
A2: 1 | B2: Front-end | C2: Auth Client | D2: ShopLogin.jsx | E2: UI page selection utilisateur - liste clients boutons + option anonyme en haut | F2: Affichage | G2: ETU003362 | H2: 20 | I2: 20 | J2: 0 | K2: =IF(H2=0,0,(H2-J2)/H2) -> 1
A3: 2 | B3: Front-end | C3: Auth Client | D3: ShopLogin.jsx | E3: Chargement clients getCustomers - filtrage active=1 et exclusion email anonyme@psgdpr.com | F3: Integration | G3: ETU003362 | H3: 25 | I3: 31 | J3: 0 | K3: =IF(H3=0,0,(H3-J3)/H3) -> 1
A4: 3 | B4: Front-end | C4: Auth Client | D4: ShopLogin.jsx | E4: Session client sessionStorage via loginAsCustomerDirect - mode demo sans verification mdp | F4: Metier | G4: ETU003362 | H4: 15 | I4: 13 | J4: 0 | K4: =IF(H4=0,0,(H4-J4)/H4) -> 1
A5: 4 | B5: Front-end | C5: Auth Client | D5: AuthContext.jsx | E5: Contexte double session employee+customer sessionStorage - loginAsCustomerDirect + logout | F5: Metier | G5: ETU003362 | H5: 15 | I5: 19 | J5: 10 | K5: =IF(H5=0,0,(H5-J5)/H5) -> 0.33333333
A6: 5 | B6: Front-end | C6: Catalogue | D6: Accueil.jsx | E6: UI grille 4 colonnes - image prix HT badge stock badge HOT/NEW selon available_date | F6: Affichage | G6: ETU003362 | H6: 30 | I6: 26 | J6: 0 | K6: =IF(H6=0,0,(H6-J6)/H6) -> 1
A7: 6 | B7: Front-end | C7: Catalogue | D7: Accueil.jsx | E7: getProducts + getCategories + getStockAvailables - stockMap id_product id_attr=0 | F7: Integration | G7: ETU003362 | H7: 25 | I7: 27 | J7: 0 | K7: =IF(H7=0,0,(H7-J7)/H7) -> 1
A8: 7 | B8: Front-end | C8: Catalogue | D8: Accueil.jsx | E8: Filtres categorie boutons + plage prix min/max + recherche nom en temps reel | F8: Metier | G8: ETU003362 | H8: 20 | I8: 14 | J8: 0 | K8: =IF(H8=0,0,(H8-J8)/H8) -> 1
A9: 8 | B9: Front-end | C9: Fiche produit | D9: FicheProduit.jsx | E9: UI detail - image description prix ajuste marque poids etat et stock restant | F9: Affichage | G9: ETU003362 | H9: 25 | I9: 25 | J9: 0 | K9: =IF(H9=0,0,(H9-J9)/H9) -> 1
A10: 9 | B10: Front-end | C10: Fiche produit | D10: FicheProduit.jsx | E10: fetchProductCombinations - groupes options valeurs stock par variante et priceImpact | F10: Integration | G10: ETU003362 | H10: 30 | I10: 36 | J10: 5 | K10: =IF(H10=0,0,(H10-J10)/H10) -> 0.83333333
A11: 10 | B11: Front-end | C11: Fiche produit | D11: FicheProduit.jsx | E11: Selection variante obligatoire - addToCart avec combinationId et validation stock | F11: Metier | G11: ETU003362 | H11: 20 | I11: 18 | J11: 0 | K11: =IF(H11=0,0,(H11-J11)/H11) -> 1
A12: 11 | B12: Front-end | C12: Panier | D12: Panier.jsx | E12: UI panier - liste articles quantite prix unitaire sous-total recapitulatif sticky | F12: Affichage | G12: ETU003362 | H12: 20 | I12: 24 | J12: 0 | K12: =IF(H12=0,0,(H12-J12)/H12) -> 1
A13: 12 | B13: Front-end | C13: Panier | D13: Panier.jsx | E13: Modification quantite suppression article vider panier via CartContext | F13: Metier | G13: ETU003362 | H13: 15 | I13: 11 | J13: 0 | K13: =IF(H13=0,0,(H13-J13)/H13) -> 1
... A47: 46 | B47: Backoffice | C47: Import CSV | D47: Import.jsx | E47: findOrCreateCategory - recherche ou creation categorie PS depuis colonne CSV produits | F47: Integration | G47: ETU003362 | H47: 25 | I47: 29 | J47: 0 | K47: =IF(H47=0,0,(H47-J47)/H47) -> 1
A48: 47 | B48: Backoffice | C48: Import CSV | D48: prestashopApi.js | E48: Pagination fetchAllPages - import 500+ lignes sans crash via limit=offset,count | F48: Integration | G48: ETU003362 | H48: 30 | I48: 30 | J48: 0 | K48: 1
A49: 48 | B49: Backoffice | C49: Reinitialisation | D49: delete_orders/customers/products.php | E49: Endpoints PHP suppression directe SQL - contourne WS 404 orders/customers/products | F49: Integration | G49: ETU003362 | H49: 40 | I49: 40 | J49: 0 | K49: 1
A50: 49 | B50: Backoffice | C50: Commandes | D50: Commandes.jsx | E50: Machine 4 etats Panier/Paiement/Livre/Annule + boutons Livrer et Annuler | F50: Metier | G50: ETU003362 | H50: 25 | I50: 25 | J50: 0 | K50: 1
A51: 50 | B51: Backoffice | C51: Tableau de bord | D51: Dashboard.jsx | E51: Stats par categorie ventes HT achats HT benefice marge via order_details WS | F51: Metier | G51: ETU003362 | H51: 35 | I51: 35 | J51: 0 | K51: 1
A52: 51 | B52: Backoffice | C52: Tableau de bord | D52: Dashboard.jsx | E52: Tableau stock par categorie Qte physique reservee disponible via stock_available | F52: Affichage | G52: ETU003362 | H52: 25 | I52: 25 | J52: 0 | K52: 1
A53: 52 | B53: Backoffice | C53: Reinitialisation | D53: Reinitialisation.jsx | E53: UI 4 modules suppression - confirmation double clic avant action irreversible | F53: Affichage | G53: ETU003362 | H53: 20 | I53: 20 | J53: 0 | K53: 1
A54: 53 | B54: Backoffice | C54: Reinitialisation | D54: Reinitialisation.jsx | E54: Suppression categories WS DELETE - tri inverse profondeur evite contrainte FK parent | F54: Integration | G54: ETU003362 | H54: 20 | I54: 20 | J54: 0 | K54: 1
A55: 54 | B55: Backoffice | C55: API | D55: prestashopApi.js | E55: loginCustomer filtre email PS WS - evite chargement total clients - filtre active et deleted | F55: Integration | G55: ETU003362 | H55: 15 | I55: 15 | J55: 0 | K55: 1
A56: 55 | B56: Backoffice | C56: API | D56: prestashopApi.js | E56: ensureGuestUser - creation user1@newapp.com au demarrage ShopLogin si inexistant | F56: Integration | G56: ETU003362 | H56: 15 | I56: 15 | J56: 0 | K56: 1
A57: Total | H57: =SUM(H2:H56) -> 1255 | I57: =SUM(I2:I56) -> 1298 | J57: =SUM(J2:J56) -> 70 | K57: =(H57-J57)/H57 -> 0.94422311

Sheet Recap
A2: Qui | B2: SUM of Estimation | C2: SUM of Temps passe | D2: SUM of Reste a faire
A3: ETU003362 | B3: ='liste des taches'!H57 -> 1255 | C3: ='liste des taches'!I57 -> 1298 | D3: ='liste des taches'!J57 -> 70
A4: Total general | B4: =B3 -> 1255 | C4: =C3 -> 1298 | D4: =D3 -> 70
A12: Avancement | B12: =avancement!D2 -> 0.94422311

Sheet avancement
A1: estimation total | B1: temps passe total | C1: reste a faire total | D1: avancement | E1: depassement
A2: ='liste des taches'!H57 -> 1255 | B2: ='liste des taches'!I57 -> 1298 | C2: ='liste des taches'!J57 -> 70 | D2: ='liste des taches'!K57 -> 0.94422311 | E2: 0.029126214
C3: =C2/60 -> 1.1666667 | D3: heure

Sheet detail_avancement
A1: Ligne | B1: Total | C1: 11/5 | D1: 12/5 | E1: 13/5 | F1: 14/5 | G1: 15/5 | H1: 16/5 | I1: 17/5 | J1: 18/5
A2: 1 | B2: 20 | C2: 0 | D2: 17 | E2: 0 | F2: 0 | G2: 0 | H2: 0 | I2: 0 | J2: 3
A3: 2 | B3: 31 | C3: 0 | D3: 0 | E3: 0 | F3: 19 | G3: 0 | H3: 12 | I3: 0 | J3: 0
A4: 3 | B4: 13 | C4: 0 | D4: 2 | E4: 0 | F4: 1 | G4: 0 | H4: 0 | I4: 10 | J4: 0
A5: 4 | B5: 19 | C5: 0 | D5: 0 | E5: 0 | F5: 4 | G5: 0 | H5: 0 | I5: 0 | J5: 15
A6: 5 | B6: 26 | C6: 7 | D6: 0 | E6: 0 | F6: 0 | G6: 7 | H6: 1 | I6: 4 | J6: 7
A7: 6 | B7: 27 | C7: 18 | D7: 0 | E7: 2 | F7: 0 | G7: 2 | H7: 1 | I7: 0 | J7: 4
A8: 7 | B8: 14 | C8: 9 | D8: 3 | E8: 0 | F8: 0 | G8: 0 | H8: 0 | I8: 0 | J8: 2
A9: 8 | B9: 25 | C9: 0 | D9: 0 | E9: 0 | F9: 0 | G9: 0 | H9: 0 | I9: 9 | J9: 16
A10: 9 | B10: 36 | C10: 0 | D10: 0 | E10: 30 | F10: 2 | G10: 0 | H10: 1 | I10: 2 | J10: 1
A11: 10 | B11: 18 | C11: 0 | D11: 0 | E11: 0 | F11: 0 | G11: 0 | H11: 8 | I11: 10 | J11: 0
A12: 11 | B12: 24 | C12: 0 | D12: 0 | E12: 0 | F12: 10 | G12: 3 | H12: 5 | I12: 6 | J12: 0
A13: 12 | B13: 11 | C13: 3 | D13: 0 | E13: 6 | F13: 0 | G13: 1 | H13: 0 | I13: 0 | J13: 1
... A52: 51 | B52: 25 | C52: 0 | D52: 0 | E52: 0 | F52: 0 | G52: 0 | H52: 0 | I52: 0 | J52: 25
B53: =SUM(B2:B52) -> 1193 | C53: =SUM(C2:C52) -> 171 | D53: =SUM(D2:D52) -> 90 | E53: =SUM(E2:E52) -> 179 | F53: =SUM(F2:F52) -> 100 | G53: =SUM(G2:G52) -> 111 | H53: =SUM(H2:H52) -> 119 | I53: =SUM(I2:I52) -> 99 | J53: =SUM(J2:J52) -> 324
